automate_machinelearning/__init__.py
automate_machinelearning-0.0.5.dist-info/LICENCE.txt
automate_machinelearning-0.0.5.dist-info/METADATA
automate_machinelearning-0.0.5.dist-info/WHEEL
automate_machinelearning-0.0.5.dist-info/top_level.txt
automate_machinelearning-0.0.5.dist-info/RECORD
