Metadata-Version: 2.1
Name: automate-machinelearning
Version: 0.0.5
Summary: A library package used to automate the machine learning on regression and classification problems.
Home-page: https://github.com/arvind444/auto_ml
Author: Arvindkumar S P
Author-email: arvindkumar1998ece@gmail.com
License: MIT
Keywords: machine_learning,correlation,outlier_handling,data,scaling,encoding
Classifier: Programming Language :: Python :: 3
Classifier: Operating System :: Microsoft :: Windows
Classifier: License :: OSI Approved :: MIT License
Requires-Python: >=3.9
License-File: LICENCE.txt
Requires-Dist: pandas
Requires-Dist: numpy
Requires-Dist: matplotlib
Requires-Dist: seaborn
Requires-Dist: joblib
Requires-Dist: scikit-learn
Requires-Dist: scipy
